mypy_boto3_codestar/__init__.py
mypy_boto3_codestar/__init__.pyi
mypy_boto3_codestar/__main__.py
mypy_boto3_codestar/client.py
mypy_boto3_codestar/client.pyi
mypy_boto3_codestar/literals.py
mypy_boto3_codestar/literals.pyi
mypy_boto3_codestar/paginator.py
mypy_boto3_codestar/paginator.pyi
mypy_boto3_codestar/py.typed
mypy_boto3_codestar/type_defs.py
mypy_boto3_codestar/type_defs.pyi
mypy_boto3_codestar/version.py
mypy_boto3_codestar-1.35.0.dist-info/LICENSE
mypy_boto3_codestar-1.35.0.dist-info/METADATA
mypy_boto3_codestar-1.35.0.dist-info/WHEEL
mypy_boto3_codestar-1.35.0.dist-info/top_level.txt
mypy_boto3_codestar-1.35.0.dist-info/RECORD
